{"scores": {"scores": {"scores": {"scores": {"szt2mikric@vasvari.org": [{"1": [5, 8]}], "szt2halpat@vasvari.org": [{"1": [4, 8]}], "szt2bukarm@vasvari.org": [{"1": [7, 8]}], "szt2agoarm@vasvari.org": [{"1": [4, 8]}], "szt2keklaj@vasvari.org": [{"1": [5, 8]}], "szt2poltam@vasvari.org": [{"1": [4, 8]}], "szt2zakbal@vasvari.org": [{"1": [8, 8]}], "szt2gemsza@vasvari.org": [{"1": [2, 8]}], "szt2mulben@vasvari.org": [{"1": [3, 8]}], "szt2peltam@vasvari.org": [{"1": [6, 8]}], "szt2makpet@vasvari.org": [{"1": [5, 8]}], "szt2hodlaj@vasvari.org": [{"1": [3, 8]}], "szt2kehsza@vasvari.org": [{"1": [3, 8]}], "szt2vetmat@vasvari.org": [{"1": [5, 8]}], "szt2bacpet@vasvari.org": [{"1": [5, 8]}], "szt2otokov@vasvari.org": [{"1": [4, 8]}], "szt2szaviv@vasvari.org": [{"1": [5, 8]}], "szt2misnan@vasvari.org": [{"1": [5, 8]}]}, "szt2mikric@vasvari.org": [{"1": [5, 8]}], "szt2halpat@vasvari.org": [{"1": [4, 8]}], "szt2bukarm@vasvari.org": [{"1": [7, 8]}], "szt2agoarm@vasvari.org": [{"1": [4, 8]}], "szt2keklaj@vasvari.org": [{"1": [5, 8]}], "szt2poltam@vasvari.org": [{"1": [4, 8]}], "szt2zakbal@vasvari.org": [{"1": [8, 8]}], "szt2gemsza@vasvari.org": [{"1": [2, 8]}], "szt2mulben@vasvari.org": [{"1": [3, 8]}], "szt2peltam@vasvari.org": [{"1": [6, 8]}], "szt2makpet@vasvari.org": [{"1": [5, 8]}], "szt2hodlaj@vasvari.org": [{"1": [3, 8]}], "szt2kehsza@vasvari.org": [{"1": [3, 8]}], "szt2vetmat@vasvari.org": [{"1": [5, 8]}], "szt2bacpet@vasvari.org": [{"1": [5, 8]}], "szt2otokov@vasvari.org": [{"1": [4, 8]}], "szt2szaviv@vasvari.org": [{"1": [5, 8]}], "szt2misnan@vasvari.org": [{"1": [5, 8]}]}, "szt2mikric@vasvari.org": [{"1": [5, 8]}], "szt2halpat@vasvari.org": [{"1": [4, 8]}], "szt2bukarm@vasvari.org": [{"1": [7, 8]}], "szt2agoarm@vasvari.org": [{"1": [4, 8]}], "szt2keklaj@vasvari.org": [{"1": [5, 8]}], "szt2poltam@vasvari.org": [{"1": [4, 8]}], "szt2zakbal@vasvari.org": [{"1": [8, 8]}], "szt2gemsza@vasvari.org": [{"1": [2, 8]}], "szt2mulben@vasvari.org": [{"1": [3, 8]}], "szt2peltam@vasvari.org": [{"1": [6, 8]}], "szt2makpet@vasvari.org": [{"1": [5, 8]}], "szt2hodlaj@vasvari.org": [{"1": [3, 8]}], "szt2kehsza@vasvari.org": [{"1": [3, 8]}], "szt2vetmat@vasvari.org": [{"1": [5, 8]}], "szt2bacpet@vasvari.org": [{"1": [5, 8]}], "szt2otokov@vasvari.org": [{"1": [4, 8]}], "szt2szaviv@vasvari.org": [{"1": [5, 8]}], "szt2misnan@vasvari.org": [{"1": [5, 8]}]}, "szt2halpat@vasvari.org": [{"2": [3, 4]}], "szt2mikric@vasvari.org": [{"2": [3, 4]}], "szt2poltam@vasvari.org": [{"2": [2, 4]}], "szt2keklaj@vasvari.org": [{"2": [2, 4]}], "szt2zakbal@vasvari.org": [{"2": [3, 4]}], "szt2mulben@vasvari.org": [{"2": [3, 4]}], "szt2peltam@vasvari.org": [{"2": [4, 4]}], "szt2makpet@vasvari.org": [{"2": [3, 4]}], "szt2hodlaj@vasvari.org": [{"2": [3, 4]}], "szt2bukarm@vasvari.org": [{"2": [3, 4]}], "szt2kehsza@vasvari.org": [{"2": [2, 4]}], "szt2vetmat@vasvari.org": [{"2": [3, 4]}], "szt2gemsza@vasvari.org": [{"2": [0, 4]}], "szt2bacpet@vasvari.org": [{"2": [2, 4]}], "szt2otokov@vasvari.org": [{"2": [3, 4]}], "szt2szaviv@vasvari.org": [{"2": [3, 4]}], "szt2misnan@vasvari.org": [{"2": [3, 4]}]}}